{
  "name": "Akashic Aurora",
  "type": "dark",
  "colors": {
    "editor.background": "#0D0C1D",
    "editor.foreground": "#E0E0E0",
    "activityBar.background": "#0A0918",
    "activityBar.foreground": "#FFFFFF",
    "activityBar.inactiveForeground": "#8F8F8F",
    "activityBarBadge.background": "#14B8A6",
    "activityBarBadge.foreground": "#0D0C1D",
    "sideBar.background": "#100F23",
    "sideBar.foreground": "#C0C0C0",
    "sideBar.border": "#1F1D33",
    "sideBarSectionHeader.background": "#15132A",
    "sideBarSectionHeader.foreground": "#E0E0E0",
    "editorGroupHeader.tabsBackground": "#0A0918",
    "tab.inactiveBackground": "#0A0918",
    "tab.activeBackground": "#15132A",
    "tab.activeForeground": "#FFFFFF",
    "tab.inactiveForeground": "#8F8F8F",
    "tab.border": "#1F1D33",
    "list.hoverBackground": "#1F1D33",
    "list.activeSelectionBackground": "#14B8A6",
    "list.activeSelectionForeground": "#0D0C1D",
    "list.focusBackground": "#1F1D33",
    "list.highlightForeground": "#14B8A6",
    "input.background": "#1F1D33",
    "input.border": "#3A385A",
    "input.foreground": "#E0E0E0",
    "input.placeholderForeground": "#7A7A90",
    "dropdown.background": "#15132A",
    "dropdown.border": "#3A385A",
    "button.background": "#14B8A6",
    "button.foreground": "#0D0C1D",
    "button.hoverBackground": "#0D9488",
    "panel.background": "#100F23",
    "panel.border": "#1F1D33",
    "peekView.border": "#14B8A6",
    "peekViewResult.background": "#15132A",
    "peekViewEditor.background": "#0D0C1D",
    "peekViewTitle.background": "#15132A",
    "statusBar.background": "#0A0918",
    "statusBar.foreground": "#A0A0A0",
    "statusBar.noFolderBackground": "#0A0918",
    "titleBar.activeBackground": "#0A0918",
    "titleBar.activeForeground": "#E0E0E0",
    "focusBorder": "#14B8A680",
    "selection.background": "#8A53E550",
    "editorWidget.background": "#15132A",
    "scrollbarSlider.background": "#3A385A",
    "scrollbarSlider.hoverBackground": "#4C4A6C",
    "scrollbarSlider.activeBackground": "#14B8A6"
  },
  "tokenColors": [
    {
      "scope": ["comment", "punctuation.definition.comment"],
      "settings": {
        "foreground": "#6C6C80",
        "fontStyle": "italic"
      }
    },
    {
      "scope": ["string", "punctuation.definition.string"],
      "settings": {
        "foreground": "#34D399"
      }
    },
    {
      "scope": ["constant.numeric", "constant.language.boolean"],
      "settings": {
        "foreground": "#A78BFA"
      }
    },
    {
      "scope": ["keyword", "storage.type", "storage.modifier"],
      "settings": {
        "foreground": "#F472B6",
        "fontStyle": "bold"
      }
    },
    {
      "scope": ["entity.name.function", "support.function"],
      "settings": {
        "foreground": "#60A5FA"
      }
    },
    {
      "scope": "variable.parameter",
      "settings": {
        "foreground": "#FBBF24",
        "fontStyle": "italic"
      }
    },
    {
      "scope": ["entity.name.tag", "punctuation.definition.tag"],
      "settings": {
        "foreground": "#8B5CF6"
      }
    },
    {
      "scope": "entity.other.attribute-name",
      "settings": {
        "foreground": "#FBBF24",
        "fontStyle": "italic"
      }
    },
    {
      "scope": "variable.language.this",
      "settings": {
        "foreground": "#F472B6",
        "fontStyle": "semi-bold"
      }
    },
    {
      "scope": ["entity.name.class", "entity.name.type"],
      "settings": {
        "foreground": "#14B8A6",
        "fontStyle": "underline"
      }
    },
    {
      "scope": "keyword.operator",
      "settings": {
        "foreground": "#8F8F8F"
      }
    },
    {
      "scope": "invalid.illegal",
      "settings": {
        "foreground": "#FF5370",
        "background": "#FF537020"
      }
    }
  ]
}
